fepdf.py
fepdf-0.1.9.dist-info/DESCRIPTION.rst
fepdf-0.1.9.dist-info/METADATA
fepdf-0.1.9.dist-info/RECORD
fepdf-0.1.9.dist-info/WHEEL
fepdf-0.1.9.dist-info/metadata.json
fepdf-0.1.9.dist-info/top_level.txt
