Metadata-Version: 2.0
Name: fepdf
Version: 0.1.9
Summary: Generacion de PDF de Facturas Electrónicas de Argentina
Home-page: https://bitbucket.org/injaon/fepdf/overview
Author: Gabriel M. Lopez
Author-email: gabriel.marcos.lopez@gmail.com
License: GNU GPL3
Keywords: AFIP PDF Factura Argentina
Platform: UNKNOWN
Classifier: Development Status :: 3 - Alpha
Classifier: Intended Audience :: Developers
Classifier: Topic :: Software Development :: Libraries :: Python Modules
Classifier: License :: OSI Approved :: GNU General Public License v3 (GPLv3)
Classifier: Programming Language :: Python :: 3
Classifier: Programming Language :: Python :: 3.3
Classifier: Programming Language :: Python :: 3.4
Classifier: Programming Language :: Python :: 3.5
Requires-Dist: fpdf
Provides-Extra: dev
Requires-Dist: pep8; extra == 'dev'
Requires-Dist: isort; extra == 'dev'
Requires-Dist: ipython; extra == 'dev'
Requires-Dist: wheel; extra == 'dev'
Requires-Dist: twine; extra == 'dev'
Provides-Extra: test
Requires-Dist: coverage; extra == 'test'
